MANIFEST.in
README.md
setup.py
typereduction/__init__.py
typereduction/makefile
typereduction/typereduction.c
typereduction/typereduction.py
typereduction.egg-info/PKG-INFO
typereduction.egg-info/SOURCES.txt
typereduction.egg-info/dependency_links.txt
typereduction.egg-info/top_level.txt