Metadata-Version: 2.1
Name: typereduction
Version: 0.2.2
Summary: Implementation of CTypes-based type reduction algorithms for using with PyIT2FLS
Home-page: https://github.com/Haghrah/PyIT2FLS/tree/master/typereduction
Author: Amir Arslan Haghrah
Author-email: arslan.haghrah@gmail.com
License: MIT
